mcp_server/README.md
mcp_server/USAGE.md
mcp_server/__init__.py
mcp_server/all_feature_server.py
mcp_server/everything_server.py
mcp_server/start.sh
mcp_server/start_mcp_servers.py
mcp_server/test_endpoints.py
mcp_server/worldcities.csv
test_server/README.md
test_server/__init__.py
test_server/generate_openapi.py
test_server/generate_postman_from_openapi.py
test_server/openapi.json
test_server/postman_collection.json
test_server/test_http_server.py
test_server/test_http_tool_integration.py
vmcp/__init__.py
vmcp/config.py
vmcp/cli/__init__.py
vmcp/cli/main.py
vmcp/data/preconfigured-servers.json
vmcp/mcps/__init__.py
vmcp/mcps/mcp_auth_manager.py
vmcp/mcps/mcp_client.py
vmcp/mcps/mcp_configmanager.py
vmcp/mcps/models.py
vmcp/mcps/models_new.py
vmcp/mcps/oauth_handler.py
vmcp/mcps/oauth_state_manager.py
vmcp/mcps/router.py
vmcp/mcps/router_typesafe.py
vmcp/proxy_server/__init__.py
vmcp/proxy_server/mcp_dependencies.py
vmcp/proxy_server/proxy_server.py
vmcp/proxy_server/proxy_server.py.backup
vmcp/proxy_server/tool_descriptions.py
vmcp/proxy_server/static/css/unauthorized.css
vmcp/proxy_server/templates/simple_unauthorized.html
vmcp/proxy_server/templates/unauthorized.html
vmcp/public_frontend/1xn-arch.png
vmcp/public_frontend/1xn-arch.svg
vmcp/public_frontend/1xn-og.jpeg
vmcp/public_frontend/1xn_logo.svg
vmcp/public_frontend/1xn_logo_ico_small.png
vmcp/public_frontend/1xn_logo_med.png
vmcp/public_frontend/1xn_logo_noframe.svg
vmcp/public_frontend/1xnlogo.png
vmcp/public_frontend/Privacy_Policy.pdf
vmcp/public_frontend/augment.svg
vmcp/public_frontend/chatgpt.svg
vmcp/public_frontend/claude-code.svg
vmcp/public_frontend/claude-desktop.svg
vmcp/public_frontend/codex.svg
vmcp/public_frontend/cursor.avif
vmcp/public_frontend/cursor.svg
vmcp/public_frontend/gemini-cli.svg
vmcp/public_frontend/highlight.svg
vmcp/public_frontend/index.html
vmcp/public_frontend/librechat.svg
vmcp/public_frontend/raycast.svg
vmcp/public_frontend/screen-1xn.png
test_pypi_vmcp-0.1.14.dist-info/METADATA
test_pypi_vmcp-0.1.14.dist-info/WHEEL
test_pypi_vmcp-0.1.14.dist-info/entry_points.txt
test_pypi_vmcp-0.1.14.dist-info/RECORD
