Metadata-Version: 2.4
Name: test-pypi-vmcp
Version: 0.1.14
Summary: v(irtual)MCP - Extend, Compose, Customize MCP servers
Project-URL: Homepage, https://github.com/vmcp/vmcp
Project-URL: Documentation, https://docs.vmcp.dev
Project-URL: Repository, https://github.com/vmcp/vmcp
Project-URL: Issues, https://github.com/vmcp/vmcp/issues
Author-email: vMCP Team <team@vmcp.dev>
License: MIT
Keywords: agents,ai,mcp,model-context-protocol,tools
Classifier: Development Status :: 4 - Beta
Classifier: Intended Audience :: Developers
Classifier: License :: OSI Approved :: MIT License
Classifier: Programming Language :: Python :: 3.10
Classifier: Programming Language :: Python :: 3.11
Classifier: Programming Language :: Python :: 3.12
Classifier: Programming Language :: Python :: 3.13
Classifier: Topic :: Software Development :: Libraries :: Python Modules
Requires-Python: <3.14,>=3.10
Requires-Dist: aiohttp<4.0.0,>=3.9.0
Requires-Dist: alembic<2.0.0,>=1.12.0
Requires-Dist: asyncpg<1.0.0,>=0.29.0
Requires-Dist: fastapi<1.0.0,>=0.104.0
Requires-Dist: httpx<1.0.0,>=0.25.0
Requires-Dist: jinja2<4.0.0,>=3.1.2
Requires-Dist: mcp>=1.0.0
Requires-Dist: opentelemetry-api<2.0.0,>=1.21.0
Requires-Dist: opentelemetry-exporter-otlp-proto-grpc>=1.21.0
Requires-Dist: opentelemetry-exporter-otlp-proto-http>=1.21.0
Requires-Dist: opentelemetry-instrumentation-asyncio>=0.42b0
Requires-Dist: opentelemetry-instrumentation-fastapi>=0.42b0
Requires-Dist: opentelemetry-instrumentation-httpx>=0.42b0
Requires-Dist: opentelemetry-instrumentation-sqlalchemy>=0.42b0
Requires-Dist: opentelemetry-instrumentation>=0.42b0
Requires-Dist: opentelemetry-sdk<2.0.0,>=1.21.0
Requires-Dist: pandas>=2.0.0
Requires-Dist: pillow>=10.0.0
Requires-Dist: psycopg2-binary<3.0.0,>=2.9.9
Requires-Dist: pydantic-settings<3.0.0,>=2.1.0
Requires-Dist: pydantic<3.0.0,>=2.5.0
Requires-Dist: python-dotenv<2.0.0,>=1.0.0
Requires-Dist: python-jose[cryptography]<4.0.0,>=3.3.0
Requires-Dist: python-multipart>=0.0.6
Requires-Dist: pytz>=2023.3
Requires-Dist: rich<14.0.0,>=13.7.0
Requires-Dist: sqlalchemy<3.0.0,>=2.0.0
Requires-Dist: starlette>=0.27.0
Requires-Dist: typer<1.0.0,>=0.9.0
Requires-Dist: uvicorn[standard]<1.0.0,>=0.24.0
Requires-Dist: websockets<13.0,>=12.0
Provides-Extra: dev
Requires-Dist: black>=23.12.0; extra == 'dev'
Requires-Dist: mypy>=1.7.1; extra == 'dev'
Requires-Dist: pre-commit>=3.5.0; extra == 'dev'
Requires-Dist: pytest-asyncio>=0.21.1; extra == 'dev'
Requires-Dist: pytest-cov>=4.1.0; extra == 'dev'
Requires-Dist: pytest-mock>=3.12.0; extra == 'dev'
Requires-Dist: pytest>=7.4.3; extra == 'dev'
Requires-Dist: ruff>=0.1.7; extra == 'dev'
